ssb/__init__.py
ssb/clusters.py
ssb/detector.py
ssb/mpc_defs.py
ssb/simulator.py
ssb/ssbplots.py
tests/__init__.py
tests/detector_tests.py
tests/simulator_tests.py
ssb_pkg-0.1.0.dist-info/LICENSE
ssb_pkg-0.1.0.dist-info/METADATA
ssb_pkg-0.1.0.dist-info/WHEEL
ssb_pkg-0.1.0.dist-info/top_level.txt
ssb_pkg-0.1.0.dist-info/RECORD
