Metadata-Version: 2.1
Name: ssb-pkg
Version: 0.1.0
Summary: A package for detecting and visualizing sinks, sources, and bridges in networks.
Home-page: https://chipdelmal.github.io/MoNeT/SSBSTP
Author: Chris De Leon
Author-email: chrisdeleon333@gmail.com
License: UNKNOWN
Platform: UNKNOWN
Classifier: Programming Language :: Python :: 3
Classifier: License :: OSI Approved :: GNU General Public License (GPL)
Requires-Python: >=3.6
